lgt/__init__.py
lgt/group/__init__.py
lgt/group/generators.py
lgt/group/group.py
lgt/lattice/__init__.py
lgt/lattice/su3/numpy/__init__.py
lgt/lattice/su3/numpy/lattice.py
lgt/lattice/su3/pytorch/__init__.py
lgt/lattice/su3/tensorflow/__init__.py
lgt/lattice/su3/tensorflow/lattice.py
lgt/lattice/sun/logm.py
lgt/lattice/sun/sun.py
lgt/lattice/u1/__init__.py
lgt/lattice/u1/numpy/__init__.py
lgt/lattice/u1/numpy/lattice.py
lgt/lattice/u1/pytorch/__init__.py
lgt/lattice/u1/pytorch/lattice.py
lgt/lattice/u1/tensorflow/__init__.py
lgt/lattice/u1/tensorflow/lattice.py
lgt-0.1.5.dist-info/LICENSE
lgt-0.1.5.dist-info/WHEEL
lgt-0.1.5.dist-info/METADATA
lgt-0.1.5.dist-info/RECORD
